inspectortodo/__init__.py
inspectortodo/config.py
inspectortodo/main.py
inspectortodo/todo.py
inspectortodo/todo_finder.py
inspectortodo/todo_validation.py
inspectortodo/parser/BaseTodoParser.py
inspectortodo/parser/BashTodoParser.py
inspectortodo/parser/Context.py
inspectortodo/parser/CsharpTodoParser.py
inspectortodo/parser/FtlTodoParser.py
inspectortodo/parser/GraphqlTodoParser.py
inspectortodo/parser/JavaScriptTodoParser.py
inspectortodo/parser/JavaTodoParser.py
inspectortodo/parser/PhpTodoParser.py
inspectortodo/parser/PythonTodoParser.py
inspectortodo/parser/XmlTodoParser.py
inspectortodo/parser/YamlTodoParser.py
inspectortodo/parser/__init__.py
inspectortodo/validator/__init__.py
inspectortodo/validator/base_validator.py
inspectortodo/validator/jira_validator.py
inspectortodo/validator/regexp_validator.py
inspectortodo/validator/versions_validator.py
inspectortodo-1.1.0.dist-info/LICENSE.md
inspectortodo-1.1.0.dist-info/METADATA
inspectortodo-1.1.0.dist-info/WHEEL
inspectortodo-1.1.0.dist-info/entry_points.txt
inspectortodo-1.1.0.dist-info/top_level.txt
inspectortodo-1.1.0.dist-info/RECORD
