Metadata-Version: 2.1
Name: inspectortodo
Version: 1.1.0
Summary: InspectorTodo is a Python tool to track the status of todos in a software project, assuming that the project uses an issue tracker, e.g. JIRA.
Home-page: https://github.com/wolfgangmuender/InspectorTodo
Author: Wolfgang Münder
Author-email: wolfgang.muender@gmail.com
Classifier: Programming Language :: Python :: 3
Classifier: License :: OSI Approved :: Apache Software License
Classifier: Operating System :: OS Independent
Classifier: Intended Audience :: Information Technology
Classifier: Topic :: Software Development :: Quality Assurance
Classifier: Environment :: Console
Requires-Python: >=3.6
License-File: LICENSE.md
Requires-Dist: click>=6.7
Requires-Dist: click-log>=0.2.1
Requires-Dist: GitPython>=2.1.9
Requires-Dist: jira>=1.0.15
